skkdictutils/__init__.py
skkdictutils/skkdictutils.py
skkdictutils-0.1.0.dist-info/METADATA
skkdictutils-0.1.0.dist-info/WHEEL
skkdictutils-0.1.0.dist-info/top_level.txt
skkdictutils-0.1.0.dist-info/RECORD
