Metadata-Version: 2.1
Name: skkdictutils
Version: 0.1.0
Summary: SKK dictionary utility functions
Home-page: https://github.com/tokuhirom/skkdictutils-py
Author: tokuhirom
Author-email: tokuhirom@gmail.com
License: MIT License
Keywords: Japanese
Platform: POSIX
Platform: Windows
Platform: Unix
Platform: MacOS
Classifier: Intended Audience :: Developers
Classifier: Intended Audience :: Information Technology
Classifier: Programming Language :: Python :: 3
Classifier: Programming Language :: Python :: 3.6
Classifier: Programming Language :: Python :: 3.7
Classifier: Programming Language :: Python :: 3.8
Classifier: License :: OSI Approved :: MIT License
Classifier: Operating System :: OS Independent
Classifier: Natural Language :: Japanese
Classifier: Topic :: Text Processing
Requires-Python: >=3.6
Requires-Dist: romkan (>=0.2.1)
